modul/__init__.py
modul/arithmetic.py
pdp_arithmet-0.0.2.dist-info/METADATA
pdp_arithmet-0.0.2.dist-info/WHEEL
pdp_arithmet-0.0.2.dist-info/top_level.txt
pdp_arithmet-0.0.2.dist-info/RECORD
