Metadata-Version: 2.1
Name: pdp-arithmet
Version: 0.0.2
Summary: Arithmetic operations package
Requires-Python: >=3.11
